izunadsp/__init__.py
izunadsp/main.py
izunadsp/misc.py
izunadsp-0.1.1.dist-info/DESCRIPTION.rst
izunadsp-0.1.1.dist-info/METADATA
izunadsp-0.1.1.dist-info/RECORD
izunadsp-0.1.1.dist-info/WHEEL
izunadsp-0.1.1.dist-info/metadata.json
izunadsp-0.1.1.dist-info/top_level.txt
